keyboardviz/__init__.py
keyboardviz/py.typed
keyboardviz-1.0.0.dist-info/WHEEL
keyboardviz-1.0.0.dist-info/METADATA
keyboardviz-1.0.0.dist-info/RECORD
