Metadata-Version: 2.3
Name: keyboardviz
Version: 1.0.0
Summary: A minimal Python library for generating keyboard layout visualizations with custom key mappings.
Author: Jo. Adly
Author-email: Jo. Adly <youssefadly237@gmail.com>
Requires-Dist: cairosvg>=2.8.2
Requires-Dist: svgwrite>=1.4.3
Requires-Python: >=3.10
Project-URL: Changelog, https://github.com/youssefadly237/keyboardviz/releases
Project-URL: Homepage, https://github.com/youssefadly237/keyboardviz
Project-URL: Issues, https://github.com/youssefadly237/keyboardviz/issues
Project-URL: Repository, https://github.com/youssefadly237/keyboardviz
